nonebot_plugin_riffusion-0.2.1.dist-info/METADATA
nonebot_plugin_riffusion-0.2.1.dist-info/WHEEL
nonebot_plugin_riffusion-0.2.1.dist-info/licenses/LICENSE
nonebot_plugin_riffusion/__init__.py
nonebot_plugin_riffusion/__main__.py
nonebot_plugin_riffusion/config.py
nonebot_plugin_riffusion/data_source.py
nonebot_plugin_riffusion-0.2.1.dist-info/RECORD
