Metadata-Version: 2.1
Name: nonebot-plugin-riffusion
Version: 0.2.1
Summary: Let AI riff a song for you.
Home-page: https://github.com/lgc-NB2Dev/nonebot-plugin-riffusion
Author-Email: student_2333 <lgc2333@126.com>
License: MIT
Project-URL: Homepage, https://github.com/lgc-NB2Dev/nonebot-plugin-riffusion
Requires-Python: <4.0,>=3.9
Requires-Dist: nonebot2>=2.2.0
Requires-Dist: nonebot-plugin-alconna>=0.40.0rc1
Requires-Dist: httpx>=0.24
